tests/__init__.py
tests/test_sample.py
tspy/__init__.py
tspy/tsp.py
tspy/lower_bounds/__init__.py
tspy/lower_bounds/held_karp.py
tspy/lower_bounds/lp.py
tspy/lower_bounds/utils.py
tspy/solvers/__init__.py
tspy/solvers/nearest_neighbor.py
tspy/solvers/twoopt.py
tspy/solvers/utils.py
tspy-0.1.1.1.dist-info/METADATA
tspy-0.1.1.1.dist-info/RECORD
tspy-0.1.1.1.dist-info/WHEEL
tspy-0.1.1.1.dist-info/top_level.txt
