Metadata-Version: 2.1
Name: tspy
Version: 0.1.1.1
Summary: An optimization package for the traveling salesman problem
Home-page: https://github.com/wborgeaud/tspy
Author: William Borgeaud
Author-email: williamborgeaud@gmail.com
License: UNKNOWN
Platform: UNKNOWN
Classifier: Development Status :: 2 - Pre-Alpha
Classifier: Programming Language :: Python
Classifier: Programming Language :: Python :: 3
Classifier: Programming Language :: Python :: 3.4
Classifier: Programming Language :: Python :: 3.5
Classifier: Programming Language :: Python :: 3.6
